external_data_structures/__init__.py
external_data_structures/dictionaries/__init__.py
external_data_structures/dictionaries/prototype.py
external_data_structures/dictionaries/s3.py
external_data_structures-0.1.0.data/data/LICENSE
external_data_structures-0.1.0.data/data/README.md
external_data_structures-0.1.0.data/data/VERSION
external_data_structures-0.1.0.dist-info/DESCRIPTION.rst
external_data_structures-0.1.0.dist-info/METADATA
external_data_structures-0.1.0.dist-info/RECORD
external_data_structures-0.1.0.dist-info/WHEEL
external_data_structures-0.1.0.dist-info/metadata.json
external_data_structures-0.1.0.dist-info/top_level.txt
