Metadata-Version: 2.0
Name: external-data-structures
Version: 0.1.0
Summary:   A set of data structure abstractions for various external data stores.
Home-page: https://github.com/mmontagna/extra-dict
Author: Marco Montagna
Author-email: marcojoemontagna@gmail.com
License: Copyright (c) 2018 Marco Montagna
Requires-Dist: generic-encoders (>=0.6.0)
Requires-Dist: recursive-itertools (>=0.2.2)
Provides-Extra: dev
Requires-Dist: moto; extra == 'dev'
Provides-Extra: s3
Requires-Dist: boto3 (>=1.7.40); extra == 's3'
